{
  "version": "1.0.0",
  "lastScanned": 1771113223344,
  "projectRoot": "/home/sany/projects/project_manager",
  "techStack": {
    "languages": [
      {
        "name": "JavaScript/TypeScript",
        "version": ">=20.0.0",
        "confidence": "high",
        "markers": [
          "package.json"
        ]
      },
      {
        "name": "TypeScript",
        "version": null,
        "confidence": "high",
        "markers": [
          "tsconfig.json"
        ]
      }
    ],
    "frameworks": [
      {
        "name": "next",
        "version": "15.1.0",
        "category": "fullstack"
      },
      {
        "name": "react",
        "version": "18.3.1",
        "category": "frontend"
      },
      {
        "name": "react-dom",
        "version": "18.3.1",
        "category": "frontend"
      },
      {
        "name": "@playwright/test",
        "version": "1.58.2",
        "category": "testing"
      },
      {
        "name": "playwright",
        "version": "1.49.1",
        "category": "testing"
      },
      {
        "name": "vitest",
        "version": "3.2.4",
        "category": "testing"
      }
    ],
    "packageManager": "npm",
    "runtime": "Node.js 20.0.0"
  },
  "build": {
    "buildCommand": "npm run build",
    "testCommand": null,
    "lintCommand": "npm run lint",
    "devCommand": "npm run dev",
    "scripts": {
      "dev": "next dev --turbopack",
      "build": "next build",
      "start": "next start",
      "lint": "next lint",
      "test:unit": "vitest",
      "test:unit:coverage": "vitest --coverage",
      "test:e2e": "playwright test",
      "test:e2e:ui": "playwright test --ui",
      "db:generate": "prisma generate",
      "db:migrate": "prisma migrate dev",
      "db:seed": "tsx prisma/seed.ts",
      "db:studio": "prisma studio",
      "format": "prettier --write .",
      "format:check": "prettier --check .",
      "typecheck": "tsc --noEmit"
    }
  },
  "conventions": {
    "namingStyle": null,
    "importStyle": null,
    "testPattern": null,
    "fileOrganization": "type-based"
  },
  "structure": {
    "isMonorepo": false,
    "workspaces": [],
    "mainDirectories": [
      "docs",
      "src",
      "tests"
    ],
    "gitBranches": {
      "defaultBranch": "main",
      "branchingStrategy": null
    }
  },
  "customNotes": [],
  "directoryMap": {
    "docs": {
      "path": "docs",
      "purpose": "Documentation",
      "fileCount": 6,
      "lastAccessed": 1771113223318,
      "keyFiles": [
        "CLARIFICATION_ANSWERS.md",
        "CLARIFICATION_QUESTIONS.md",
        "FINAL_TECHNICAL_SPECIFICATION.md",
        "OPTIMIZED_FINAL_SPECIFICATION.md",
        "TECHNICAL_SPECIFICATION_V3.md"
      ]
    },
    "prisma": {
      "path": "prisma",
      "purpose": null,
      "fileCount": 4,
      "lastAccessed": 1771113223320,
      "keyFiles": [
        "dev.db",
        "password-reset-token.prisma",
        "schema.prisma",
        "seed.ts"
      ]
    },
    "src": {
      "path": "src",
      "purpose": "Source code",
      "fileCount": 1,
      "lastAccessed": 1771113223332,
      "keyFiles": [
        "middleware.ts"
      ]
    },
    "tests": {
      "path": "tests",
      "purpose": "Test files",
      "fileCount": 1,
      "lastAccessed": 1771113223333,
      "keyFiles": [
        "setup.ts"
      ]
    },
    "prisma/migrations": {
      "path": "prisma/migrations",
      "purpose": "Database migrations",
      "fileCount": 1,
      "lastAccessed": 1771113223334,
      "keyFiles": [
        "migration_lock.toml"
      ]
    },
    "prisma/tests": {
      "path": "prisma/tests",
      "purpose": "Test files",
      "fileCount": 0,
      "lastAccessed": 1771113223334,
      "keyFiles": []
    },
    "src/app": {
      "path": "src/app",
      "purpose": "Application code",
      "fileCount": 4,
      "lastAccessed": 1771113223334,
      "keyFiles": [
        "globals.css",
        "layout.tsx",
        "page.tsx"
      ]
    },
    "src/components": {
      "path": "src/components",
      "purpose": "UI components",
      "fileCount": 0,
      "lastAccessed": 1771113223335,
      "keyFiles": []
    },
    "src/lib": {
      "path": "src/lib",
      "purpose": "Library code",
      "fileCount": 4,
      "lastAccessed": 1771113223335,
      "keyFiles": [
        "db.ts",
        "prisma.ts",
        "queryClient.ts"
      ]
    },
    "src/middleware": {
      "path": "src/middleware",
      "purpose": "Middleware",
      "fileCount": 0,
      "lastAccessed": 1771113223336,
      "keyFiles": []
    },
    "src/types": {
      "path": "src/types",
      "purpose": "Type definitions",
      "fileCount": 3,
      "lastAccessed": 1771113223336,
      "keyFiles": [
        "api.ts",
        "project.ts",
        "tag.ts"
      ]
    },
    "tests/mocks": {
      "path": "tests/mocks",
      "purpose": "Mock data",
      "fileCount": 2,
      "lastAccessed": 1771113223337,
      "keyFiles": [
        "factories.ts",
        "handlers.ts"
      ]
    }
  },
  "hotPaths": [
    {
      "path": "prisma/schema.prisma",
      "accessCount": 51,
      "lastAccessed": 1771173006195,
      "type": "file"
    },
    {
      "path": "src/app/projects/[id]/reviews/[reviewId]/page.tsx",
      "accessCount": 27,
      "lastAccessed": 1771135170447,
      "type": "file"
    },
    {
      "path": "src",
      "accessCount": 25,
      "lastAccessed": 1771172721916,
      "type": "directory"
    },
    {
      "path": "src/app/api/v1/projects/route.ts",
      "accessCount": 24,
      "lastAccessed": 1771173138027,
      "type": "file"
    },
    {
      "path": "src/app/api/v1/notifications/route.ts",
      "accessCount": 17,
      "lastAccessed": 1771172678044,
      "type": "file"
    },
    {
      "path": "src/app/api/v1/files/[id]/route.ts",
      "accessCount": 13,
      "lastAccessed": 1771173101550,
      "type": "file"
    },
    {
      "path": "src/app/api/v1/reviews/[id]/route.ts",
      "accessCount": 12,
      "lastAccessed": 1771133672599,
      "type": "file"
    },
    {
      "path": "src/app/api/v1/reviews/[id]/participants/route.ts",
      "accessCount": 12,
      "lastAccessed": 1771133933633,
      "type": "file"
    },
    {
      "path": "src/app/api/v1/files/upload/route.ts",
      "accessCount": 12,
      "lastAccessed": 1771172680243,
      "type": "file"
    },
    {
      "path": "src/app/api/v1/risks/route.ts",
      "accessCount": 10,
      "lastAccessed": 1771172679898,
      "type": "file"
    },
    {
      "path": "prisma",
      "accessCount": 9,
      "lastAccessed": 1771134544930,
      "type": "directory"
    },
    {
      "path": "src/app/api/v1/preview/services/[id]/route.ts",
      "accessCount": 8,
      "lastAccessed": 1771132502557,
      "type": "file"
    },
    {
      "path": "src/app/projects/[id]/reviews/page.tsx",
      "accessCount": 8,
      "lastAccessed": 1771135312584,
      "type": "file"
    },
    {
      "path": "src/app/api/v1/signature/route.ts",
      "accessCount": 8,
      "lastAccessed": 1771172678114,
      "type": "file"
    },
    {
      "path": "src/app/api/v1/reviews/[id]/materials/route.ts",
      "accessCount": 7,
      "lastAccessed": 1771132837312,
      "type": "file"
    },
    {
      "path": "src/components/dashboard/TaskTimeline.tsx",
      "accessCount": 7,
      "lastAccessed": 1771161002050,
      "type": "file"
    },
    {
      "path": "src/components/risks/RiskMatrix.tsx",
      "accessCount": 7,
      "lastAccessed": 1771161011369,
      "type": "file"
    },
    {
      "path": "src/app/api/v1/dashboard/my-tasks/route.ts",
      "accessCount": 7,
      "lastAccessed": 1771161370361,
      "type": "file"
    },
    {
      "path": "src/app/projects/[id]/risks/page.tsx",
      "accessCount": 6,
      "lastAccessed": 1771135353795,
      "type": "file"
    },
    {
      "path": "src/lib/api/response.ts",
      "accessCount": 6,
      "lastAccessed": 1771161019504,
      "type": "file"
    },
    {
      "path": "src/app/api",
      "accessCount": 5,
      "lastAccessed": 1771161011073,
      "type": "directory"
    },
    {
      "path": "src/app/api/v1/dashboard/progress/route.ts",
      "accessCount": 5,
      "lastAccessed": 1771161370287,
      "type": "file"
    },
    {
      "path": "src/app/api/v1/files/preview/route.ts",
      "accessCount": 5,
      "lastAccessed": 1771173102482,
      "type": "file"
    },
    {
      "path": "src/app/api/v1/reviews.disabled/[id]/route.ts",
      "accessCount": 4,
      "lastAccessed": 1771135109675,
      "type": "file"
    },
    {
      "path": "src/app/api/v1/dashboard/stats/route.ts",
      "accessCount": 4,
      "lastAccessed": 1771161370268,
      "type": "file"
    },
    {
      "path": "package.json",
      "accessCount": 4,
      "lastAccessed": 1771172383818,
      "type": "file"
    },
    {
      "path": "src/app/api/v1/preview/services/route.ts",
      "accessCount": 4,
      "lastAccessed": 1771172711356,
      "type": "file"
    },
    {
      "path": "src/app/api/v1/reviews.disabled/route.ts",
      "accessCount": 4,
      "lastAccessed": 1771172711429,
      "type": "file"
    },
    {
      "path": "src/app/api/v1/notifications/ignore/route.ts",
      "accessCount": 4,
      "lastAccessed": 1771173099914,
      "type": "file"
    },
    {
      "path": "src/app/api/v1/notifications/preferences/route.ts",
      "accessCount": 4,
      "lastAccessed": 1771173100778,
      "type": "file"
    },
    {
      "path": "src/components/views/MaterialUpload.tsx",
      "accessCount": 3,
      "lastAccessed": 1771131015921,
      "type": "file"
    },
    {
      "path": "src/components/risks/RiskTaskLink.tsx",
      "accessCount": 3,
      "lastAccessed": 1771131163442,
      "type": "file"
    },
    {
      "path": "src/components/views/materialUpload.tsx",
      "accessCount": 2,
      "lastAccessed": 1771130655177,
      "type": "file"
    },
    {
      "path": "src/app/api/v1/dashboard/route.ts",
      "accessCount": 2,
      "lastAccessed": 1771130746649,
      "type": "file"
    },
    {
      "path": "src/components/views/AddParticipant.tsx",
      "accessCount": 2,
      "lastAccessed": 1771130855685,
      "type": "file"
    },
    {
      "path": "src/components/views/ReviewItemForm.tsx",
      "accessCount": 2,
      "lastAccessed": 1771130855743,
      "type": "file"
    },
    {
      "path": "src/components/risks/RiskProgress.tsx",
      "accessCount": 2,
      "lastAccessed": 1771131046716,
      "type": "file"
    },
    {
      "path": "src/app/api/v1/reviews/[id]/items/route.ts",
      "accessCount": 2,
      "lastAccessed": 1771131497770,
      "type": "file"
    },
    {
      "path": "src/app",
      "accessCount": 2,
      "lastAccessed": 1771132006326,
      "type": "directory"
    },
    {
      "path": "src/app/api/v1/reviews.disabled/types/route.ts",
      "accessCount": 2,
      "lastAccessed": 1771134901639,
      "type": "file"
    },
    {
      "path": "src/components/notifications/NotificationIcon.tsx",
      "accessCount": 1,
      "lastAccessed": 1771113822465,
      "type": "file"
    },
    {
      "path": "src/components/notifications/NotificationDrawer.tsx",
      "accessCount": 1,
      "lastAccessed": 1771113839389,
      "type": "file"
    },
    {
      "path": "src/components/tasks/TaskTimeline.tsx",
      "accessCount": 1,
      "lastAccessed": 1771114721219,
      "type": "file"
    },
    {
      "path": "src/components/files/PreviewServiceConfig.tsx",
      "accessCount": 1,
      "lastAccessed": 1771114836252,
      "type": "file"
    },
    {
      "path": "tsconfig.json",
      "accessCount": 1,
      "lastAccessed": 1771115428922,
      "type": "file"
    },
    {
      "path": "src/app/api/v1/dashboard",
      "accessCount": 1,
      "lastAccessed": 1771130726577,
      "type": "directory"
    },
    {
      "path": "src/app/projects/[id]/reviews/[reviewId]",
      "accessCount": 1,
      "lastAccessed": 1771130739681,
      "type": "directory"
    },
    {
      "path": "src/lib/api",
      "accessCount": 1,
      "lastAccessed": 1771131006817,
      "type": "directory"
    },
    {
      "path": "src/lib/api/client.ts",
      "accessCount": 1,
      "lastAccessed": 1771131006896,
      "type": "file"
    },
    {
      "path": "src/app/api/v1/email/configs/route.ts",
      "accessCount": 1,
      "lastAccessed": 1771132302994,
      "type": "file"
    }
  ],
  "userDirectives": []
}